odoo10_addon_account_payment_partner-10.0.1.1.2-py2.7-nspkg.pth
odoo/addons/account_payment_partner/README.rst
odoo/addons/account_payment_partner/__init__.py
odoo/addons/account_payment_partner/__manifest__.py
odoo/addons/account_payment_partner/demo/partner_demo.xml
odoo/addons/account_payment_partner/i18n/ca.po
odoo/addons/account_payment_partner/i18n/da_DK.po
odoo/addons/account_payment_partner/i18n/de.po
odoo/addons/account_payment_partner/i18n/es.po
odoo/addons/account_payment_partner/i18n/fr.po
odoo/addons/account_payment_partner/i18n/hr.po
odoo/addons/account_payment_partner/i18n/nb_NO.po
odoo/addons/account_payment_partner/i18n/nl.po
odoo/addons/account_payment_partner/i18n/nl_NL.po
odoo/addons/account_payment_partner/i18n/pt_BR.po
odoo/addons/account_payment_partner/i18n/sl.po
odoo/addons/account_payment_partner/models/__init__.py
odoo/addons/account_payment_partner/models/account_invoice.py
odoo/addons/account_payment_partner/models/account_move_line.py
odoo/addons/account_payment_partner/models/res_partner.py
odoo/addons/account_payment_partner/static/description/icon.png
odoo/addons/account_payment_partner/views/account_invoice_view.xml
odoo/addons/account_payment_partner/views/account_move_line.xml
odoo/addons/account_payment_partner/views/report_invoice.xml
odoo/addons/account_payment_partner/views/res_partner_view.xml
odoo10_addon_account_payment_partner-10.0.1.1.2.dist-info/DESCRIPTION.rst
odoo10_addon_account_payment_partner-10.0.1.1.2.dist-info/METADATA
odoo10_addon_account_payment_partner-10.0.1.1.2.dist-info/RECORD
odoo10_addon_account_payment_partner-10.0.1.1.2.dist-info/WHEEL
odoo10_addon_account_payment_partner-10.0.1.1.2.dist-info/metadata.json
odoo10_addon_account_payment_partner-10.0.1.1.2.dist-info/namespace_packages.txt
odoo10_addon_account_payment_partner-10.0.1.1.2.dist-info/top_level.txt
